{
  "milestone_id": "M4.6",
  "status": "PASS",
  "generated_at": "2026-03-30T23:24:53+00:00",
  "git_head": "ecc1e76b6be04127204d5935075b49d9295c6fb6",
  "seed_set": [
    46,
    146,
    246,
    346
  ],
  "artifacts": {
    "trace": "E:\\workspace\\segments\\artifacts\\m46_longitudinal_trace.json",
    "divergence": "E:\\workspace\\segments\\artifacts\\m46_style_divergence.json",
    "recovery": "E:\\workspace\\segments\\artifacts\\m46_recovery_retention.json",
    "stress": "E:\\workspace\\segments\\artifacts\\m46_corruption_stress.json",
    "summary": "E:\\workspace\\segments\\reports\\m46_acceptance_summary.md",
    "regressions": {
      "m45": {
        "trace": "E:\\workspace\\segments\\artifacts\\m45_open_world_trace.json",
        "mapping": "E:\\workspace\\segments\\artifacts\\m45_parameter_projection.json",
        "ablation": "E:\\workspace\\segments\\artifacts\\m45_open_world_ablation.json",
        "stress": "E:\\workspace\\segments\\artifacts\\m45_open_world_stress.json",
        "report": "E:\\workspace\\segments\\reports\\m45_acceptance_report.json",
        "summary": "E:\\workspace\\segments\\reports\\m45_acceptance_summary.md"
      },
      "m44": {
        "trace": "E:\\workspace\\segments\\artifacts\\m44_cross_task_trace.json",
        "shared_vs_independent": "E:\\workspace\\segments\\artifacts\\m44_shared_vs_independent.json",
        "ablation": "E:\\workspace\\segments\\artifacts\\m44_cross_task_ablation.json",
        "stress": "E:\\workspace\\segments\\artifacts\\m44_cross_task_stress.json",
        "report": "E:\\workspace\\segments\\reports\\m44_acceptance_report.json",
        "summary": "E:\\workspace\\segments\\reports\\m44_acceptance_summary.md"
      },
      "m43": {
        "trace": "E:\\workspace\\segments\\artifacts\\m43_confidence_fit_trace.json",
        "baselines": "E:\\workspace\\segments\\artifacts\\m43_baseline_comparison.json",
        "ablation": "E:\\workspace\\segments\\artifacts\\m43_confidence_ablation.json",
        "stress": "E:\\workspace\\segments\\artifacts\\m43_confidence_stress.json",
        "failure_analysis": "E:\\workspace\\segments\\artifacts\\m43_failure_analysis.json",
        "report": "E:\\workspace\\segments\\reports\\m43_acceptance_report.json",
        "summary": "E:\\workspace\\segments\\reports\\m43_acceptance_summary.md"
      },
      "m236": {
        "trace": "E:\\workspace\\segments\\artifacts\\m236_open_continuity_trace.jsonl",
        "metrics": "E:\\workspace\\segments\\artifacts\\m236_open_continuity_metrics.json",
        "ablation": "E:\\workspace\\segments\\artifacts\\m236_open_continuity_ablation.json",
        "stress": "E:\\workspace\\segments\\artifacts\\m236_open_continuity_stress.json",
        "schema": "E:\\workspace\\segments\\artifacts\\m236_open_continuity_schema.json",
        "report": "E:\\workspace\\segments\\reports\\m236_open_continuity_report.json",
        "summary": "E:\\workspace\\segments\\reports\\m236_open_continuity_summary.md"
      }
    }
  },
  "tests": {
    "milestone": [
      "tests/test_m46_style_stability.py",
      "tests/test_m46_style_divergence.py",
      "tests/test_m46_recovery_retention.py",
      "tests/test_m46_acceptance.py"
    ],
    "regressions": [
      "tests/test_m45_acceptance.py",
      "tests/test_m44_acceptance.py",
      "tests/test_m43_acceptance.py",
      "tests/test_m236_acceptance.py"
    ]
  },
  "gates": {
    "schema": {
      "passed": true
    },
    "determinism": {
      "passed": true
    },
    "causality": {
      "passed": true
    },
    "ablation": {
      "passed": true
    },
    "stress": {
      "passed": true
    },
    "regression": {
      "passed": true
    },
    "artifact_freshness": {
      "passed": true
    }
  },
  "findings": [],
  "headline_metrics": {
    "trial_count": 12,
    "subject_count": 3,
    "synthetic": true,
    "external_bundle": false,
    "split_unit": "persistent_state",
    "claim_envelope": "synthetic_probe_only",
    "synthetic_probe": true,
    "live_integration": false
  },
  "readiness": {
    "deployment_readiness": "NOT_READY",
    "claim_envelope": "synthetic_projection_only",
    "warning_count": 2,
    "warnings": [],
    "strengths": [
      "Behavior remains task-consistent under the synthetic probe.",
      "Failure recovery remains available under stress."
    ],
    "blocking_gaps": [
      "M4.6 still operates on a synthetic environment scaffold.",
      "M4.6 has no live tool or environment integration yet."
    ],
    "metrics_snapshot": {
      "goal_consistency_rate": 0.695921,
      "adaptive_recovery_rate": 1.0,
      "synthetic_environment": true,
      "live_integration": false
    }
  },
  "residual_risks": [
    "M4.6 still measures long-horizon style over a synthetic repeated open-world scaffold rather than a live persistent environment."
  ],
  "freshness": {
    "generated_this_round": true,
    "round_started_at": "2026-03-30T23:23:57+00:00"
  },
  "recommendation": "ACCEPT"
}