{
  "milestone_id": "M4.8",
  "status": "PASS",
  "generated_at": "2026-04-09T12:18:19+00:00",
  "git_head": "63027b6c52459076654706a9c680cb622815506e",
  "seed_set": [
    45,
    145
  ],
  "artifacts": {
    "trace": "E:\\workspace\\segments\\artifacts\\m48_open_world_trace.json",
    "mapping": "E:\\workspace\\segments\\artifacts\\m48_parameter_projection.json",
    "ablation": "E:\\workspace\\segments\\artifacts\\m48_open_world_ablation.json",
    "stress": "E:\\workspace\\segments\\artifacts\\m48_open_world_stress.json",
    "summary": "E:\\workspace\\segments\\reports\\m48_acceptance_summary.md",
    "regressions": {
      "m44": {
        "joint_fit": "E:\\workspace\\segments\\artifacts\\m44_joint_fit.json",
        "degradation": "E:\\workspace\\segments\\artifacts\\m44_degradation.json",
        "parameter_stability": "E:\\workspace\\segments\\artifacts\\m44_parameter_stability.json",
        "weight_sensitivity": "E:\\workspace\\segments\\artifacts\\m44_weight_sensitivity.json",
        "igt_aggregate": "E:\\workspace\\segments\\artifacts\\m44_igt_aggregate.json",
        "architecture_assessment": "E:\\workspace\\segments\\artifacts\\m44_architecture_assessment.json",
        "report": "E:\\workspace\\segments\\reports\\m44_acceptance_report.json",
        "summary": "E:\\workspace\\segments\\reports\\m44_acceptance_summary.md"
      },
      "m36": {
        "trace": "E:\\workspace\\segments\\artifacts\\m36_open_world_growth_trace.json",
        "ablation": "E:\\workspace\\segments\\artifacts\\m36_open_world_growth_ablation.json",
        "stress": "E:\\workspace\\segments\\artifacts\\m36_open_world_growth_stress.json",
        "snapshots": "E:\\workspace\\segments\\artifacts\\m36_open_world_growth_snapshots.json",
        "failure_audit": "E:\\workspace\\segments\\artifacts\\m36_open_world_growth_failure_audit.json",
        "report": "E:\\workspace\\segments\\reports\\m36_acceptance_report.json",
        "summary": "E:\\workspace\\segments\\reports\\m36_acceptance_summary.md"
      }
    }
  },
  "tests": {
    "milestone": [
      "tests/test_m48_parameter_projection.py",
      "tests/test_m48_failure_recovery.py",
      "tests/test_m48_acceptance.py"
    ],
    "regressions": [
      "tests/test_m44_acceptance.py",
      "tests/test_m36_acceptance.py"
    ]
  },
  "gates": {
    "schema": {
      "passed": true
    },
    "determinism": {
      "passed": true
    },
    "causality": {
      "passed": true
    },
    "ablation": {
      "passed": true
    },
    "stress": {
      "passed": true
    },
    "regression": {
      "passed": true
    },
    "artifact_freshness": {
      "passed": true
    },
    "parameter_projection": {
      "passed": true
    }
  },
  "findings": [],
  "headline_metrics": {
    "trial_count": 3,
    "subject_count": 0,
    "synthetic": true,
    "external_bundle": false,
    "split_unit": "n/a",
    "claim_envelope": "synthetic_probe_only",
    "synthetic_probe": true,
    "live_integration": true
  },
  "readiness": {
    "deployment_readiness": "NOT_READY",
    "claim_envelope": "synthetic_projection_only",
    "warning_count": 1,
    "warnings": [],
    "strengths": [
      "Behavior remains task-consistent under the synthetic probe.",
      "Failure recovery remains available under stress."
    ],
    "blocking_gaps": [
      "M4.8 still operates on a synthetic environment scaffold."
    ],
    "metrics_snapshot": {
      "goal_consistency_rate": 1.0,
      "adaptive_recovery_rate": 1.0,
      "synthetic_environment": true,
      "live_integration": true
    }
  },
  "residual_risks": [
    "M4.8 remains a tool-shaped synthetic open-world trial rather than a live external environment integration."
  ],
  "freshness": {
    "generated_this_round": true,
    "round_started_at": "2026-04-09T00:00:00+00:00"
  },
  "recommendation": "ACCEPT"
}